{
    "prediction": [
                   {
                   "description": "Bowie Street, Austin, TX, United States",
                   "placeId": "EidCb3dpZSBTdHJlZXQsIEF1c3RpbiwgVFgsIFVuaXRlZCBTdGF0ZXM",
                   "types": [
                             "route",
                             "geocode"
                             ],
                   "matches": [
                               {
                               "offset": 0,
                               "length": 12
                               },
                               {
                               "offset": 14,
                               "length": 6
                               }
                               ],
                   "structuredFormatting": {
                   "description": "Bowie Street",
                   "subDescription": "Austin, TX, United States",
                   "descriptionMatches": [
                                          {
                                          "offset": 0,
                                          "length": 12
                                          }
                                          ],
                   "subDescriptionMatches": [
                                             {
                                             "offset": 0,
                                             "length": 6
                                             }
                                             ]
                   }
                   },
                   {
                   "description": "Bowie Road, Austin, TX, United States",
                   "placeId": "EiVCb3dpZSBSb2FkLCBBdXN0aW4sIFRYLCBVbml0ZWQgU3RhdGVz",
                   "types": [
                             "route",
                             "geocode"
                             ],
                   "matches": [
                               {
                               "offset": 0,
                               "length": 10
                               },
                               {
                               "offset": 12,
                               "length": 6
                               }
                               ],
                   "structuredFormatting": {
                   "description": "Bowie Road",
                   "subDescription": "Austin, TX, United States",
                   "descriptionMatches": [
                                          {
                                          "offset": 0,
                                          "length": 10
                                          }
                                          ],
                   "subDescriptionMatches": [
                                             {
                                             "offset": 0,
                                             "length": 6
                                             }
                                             ]
                   }
                   },
                   {
                   "description": "Bowie Underpass, Austin, TX, United States",
                   "placeId": "EipCb3dpZSBVbmRlcnBhc3MsIEF1c3RpbiwgVFgsIFVuaXRlZCBTdGF0ZXM",
                   "types": [
                             "route",
                             "geocode"
                             ],
                   "matches": [
                               {
                               "offset": 0,
                               "length": 15
                               },
                               {
                               "offset": 17,
                               "length": 6
                               }
                               ],
                   "structuredFormatting": {
                   "description": "Bowie Underpass",
                   "subDescription": "Austin, TX, United States",
                   "descriptionMatches": [
                                          {
                                          "offset": 0,
                                          "length": 15
                                          }
                                          ],
                   "subDescriptionMatches": [
                                             {
                                             "offset": 0,
                                             "length": 6
                                             }
                                             ]
                   }
                   },
                   {
                   "description": "Austin Metropolitan Area, Bowie Street, Bartlett, TX, United States",
                   "placeId": "EkNBdXN0aW4gTWV0cm9wb2xpdGFuIEFyZWEsIEJvd2llIFN0cmVldCwgQmFydGxldHQsIFRYLCBVbml0ZWQgU3RhdGVz",
                   "types": [
                             "route",
                             "geocode"
                             ],
                   "matches": [
                               {
                               "offset": 0,
                               "length": 6
                               },
                               {
                               "offset": 26,
                               "length": 12
                               }
                               ],
                   "structuredFormatting": {
                   "description": "Bowie Street",
                   "subDescription": "Austin Metropolitan Area, Bartlett, TX, United States",
                   "descriptionMatches": [
                                          {
                                          "offset": 0,
                                          "length": 12
                                          }
                                          ],
                   "subDescriptionMatches": [
                                             {
                                             "offset": 0,
                                             "length": 6
                                             }
                                             ]
                   }
                   },
                   {
                   "description": "Austin Metropolitan Area, Bowie Street, Lockhart, TX, United States",
                   "placeId": "EkNBdXN0aW4gTWV0cm9wb2xpdGFuIEFyZWEsIEJvd2llIFN0cmVldCwgTG9ja2hhcnQsIFRYLCBVbml0ZWQgU3RhdGVz",
                   "types": [
                             "route",
                             "geocode"
                             ],
                   "matches": [
                               {
                               "offset": 0,
                               "length": 6
                               },
                               {
                               "offset": 26,
                               "length": 12
                               }
                               ],
                   "structuredFormatting": {
                   "description": "Bowie Street",
                   "subDescription": "Austin Metropolitan Area, Lockhart, TX, United States",
                   "descriptionMatches": [
                                          {
                                          "offset": 0,
                                          "length": 12
                                          }
                                          ],
                   "subDescriptionMatches": [
                                             {
                                             "offset": 0,
                                             "length": 6
                                             }
                                             ]
                   }
                   }
                   ]
}
